[{"j":"CL","c":"143","l":"LICEUL TEHNOLOGIC \"SANDU ALDEA\" CALARASI","n":"Liceal","sp":"Agricultură","nll":"6","lp":"Limba română","lb":"-","p":"Resurse naturale și protecția mediului","f":"Tehnologică","fi":"Zi","m":"URBAN","la":"CĂLĂRAŞI STR PREL. BUCURESTI NR  10","lt":"0242334666"},{"j":"CL","c":"139","l":"LICEUL TEHNOLOGIC NR.1 FUNDULEA","n":"Liceal","sp":"Agricultură","nll":"23","lp":"Limba română","lb":"-","p":"Resurse naturale și protecția mediului","f":"Tehnologică","fi":"Zi","m":"URBAN","la":"FUNDULEA STR NICOLAE TITULESCU NR 5","lt":"0242642079"},{"j":"CL","c":"142","l":"LICEUL TEHNOLOGIC NR.1 FUNDULEA","n":"Liceal","sp":"Protecţia mediului","nll":"14","lp":"Limba română","lb":"-","p":"Resurse naturale și protecția mediului","f":"Tehnologică","fi":"Zi","m":"URBAN","la":"FUNDULEA STR NICOLAE TITULESCU NR 5","lt":"0242642079"},{"j":"CL","c":"101","l":"COLEGIUL ECONOMIC CALARASI","n":"Liceal","sp":"Economic","nll":"9","lp":"Limba română","lb":"-","p":"Servicii","f":"Tehnologică","fi":"Zi","m":"URBAN","la":"CĂLĂRAŞI STR 1 DECEMBRIE 1918  NR  88","lt":"0242312142"},{"j":"CL","c":"125","l":"LICEUL TEHNOLOGIC \"DAN MATEESCU\" CALARASI","n":"Liceal","sp":"Estetica şi igiena corpului omenesc","nll":"11","lp":"Limba română","lb":"-","p":"Servicii","f":"Tehnologică","fi":"Zi","m":"URBAN","la":"CĂLĂRAŞI STR PRELUNGIREA BUCURESTI NR  8-12","lt":"0242334312"},{"j":"CL","c":"128","l":"LICEUL TEHNOLOGIC \"ION GHICA\" OLTENITA","n":"Liceal","sp":"Estetica şi igiena corpului omenesc","nll":"14","lp":"Limba română","lb":"-","p":"Servicii","f":"Tehnologică","fi":"Zi","m":"URBAN","la":"OLTENIŢA STR ARGESULUI NR  100","lt":"0242515729"},{"j":"CL","c":"121","l":"LICEUL PEDAGOGIC \"STEFAN BANULESCU\" CALARASI","n":"Liceal","sp":"Turism şi alimentaţie","nll":"3","lp":"Limba română","lb":"-","p":"Servicii","f":"Tehnologică","fi":"Zi","m":"URBAN","la":"CĂLĂRAŞI STR PREL. BUCURESTI NR  1","lt":"0242312308"},{"j":"CL","c":"102","l":"COLEGIUL ECONOMIC CALARASI","n":"Liceal","sp":"Turism şi alimentaţie","nll":"18","lp":"Limba română","lb":"-","p":"Servicii","f":"Tehnologică","fi":"Zi","m":"URBAN","la":"CĂLĂRAŞI STR 1 DECEMBRIE 1918  NR  88","lt":"0242312142"},{"j":"CL","c":"131","l":"LICEUL TEHNOLOGIC \"NICOLAE BALCESCU\" OLTENITA","n":"Liceal","sp":"Electronică automatizări","nll":"13","lp":"Limba română","lb":"-","p":"Tehnic","f":"Tehnologică","fi":"Zi","m":"URBAN","la":"OLTENIŢA STR PORTULUI  NR  3","lt":"0242515792"},{"j":"CL","c":"135","l":"LICEUL TEHNOLOGIC \"NICOLAE BALCESCU\" OLTENITA","n":"Liceal","sp":"Mecanică","nll":"14","lp":"Limba română","lb":"-","p":"Tehnic","f":"Tehnologică","fi":"Zi","m":"URBAN","la":"OLTENIŢA STR PORTULUI  NR  3","lt":"0242515792"},{"j":"CL","c":"133","l":"LICEUL TEHNOLOGIC \"NICOLAE BALCESCU\" OLTENITA","n":"Liceal","sp":"Industrie textilă şi pielărie","nll":"18","lp":"Limba română","lb":"-","p":"Tehnic","f":"Tehnologică","fi":"Zi","m":"URBAN","la":"OLTENIŢA STR PORTULUI  NR  3","lt":"0242515792"},{"j":"CL","c":"112","l":"LICEUL \"ALEXANDRU ODOBESCU\" LEHLIU GARA","n":"Liceal","sp":"Matematică-Informatică","nll":"9","lp":"Limba română","lb":"-","p":"Real","f":"Teoretică","fi":"Zi","m":"URBAN","la":"LEHLIU-GARĂ STR VIITORULUI NR 9","lt":"0242640115"},{"j":"CL","c":"134","l":"LICEUL TEHNOLOGIC \"NICOLAE BALCESCU\" OLTENITA","n":"Liceal","sp":"Matematică-Informatică","nll":"2","lp":"Limba română","lb":"-","p":"Real","f":"Teoretică","fi":"Zi","m":"URBAN","la":"OLTENIŢA STR PORTULUI  NR  3","lt":"0242515792"},{"j":"CL","c":"138","l":"LICEUL TEHNOLOGIC NR.1 BORCEA","n":"Liceal","sp":"Agricultură","nll":"15","lp":"Limba română","lb":"-","p":"Resurse naturale și protecția mediului","f":"Tehnologică","fi":"Zi","m":"RURAL","la":"BORCEA STR SCOLII NR 10B","lt":"0242340029"},{"j":"CL","c":"129","l":"LICEUL TEHNOLOGIC \"MATEI BASARAB\" MANASTIREA","n":"Liceal","sp":"Agricultură","nll":"24","lp":"Limba română","lb":"-","p":"Resurse naturale și protecția mediului","f":"Tehnologică","fi":"Zi","m":"RURAL","la":"MÂNĂSTIREA STR  SOSEAUA OLTENITEI NR  79","lt":"0242520017"},{"j":"CL","c":"123","l":"LICEUL TEHNOLOGIC \"CONSTANTIN GEORGE CALINESCU\" GRADISTEA","n":"Liceal","sp":"Industrie alimentară","nll":"26","lp":"Limba română","lb":"-","p":"Resurse naturale și protecția mediului","f":"Tehnologică","fi":"Zi","m":"RURAL","la":"GRĂDIŞTEA STR  CALEA CALARASI NR  108","lt":"0242336518"}]