[{"j":"SV","c":"232","l":"LICEUL TEHNOLOGIC \"NICOLAI NANU\" BROȘTENI","n":"Liceal","sp":"Matematică-Informatică","nll":"4","lp":"Limba română","lb":"-","p":"Real","f":"Teoretică","fi":"Zi","m":"URBAN","la":"BROŞTENI STR  NICOLAE NANU NR 3","lt":"0230549783"},{"j":"SV","c":"221","l":"LICEUL TEHNOLOGIC \"ION NISTOR\" VICOVU DE SUS","n":"Liceal","sp":"Industrie textilă şi pielărie","nll":"22","lp":"Limba română","lb":"-","p":"Tehnic","f":"Tehnologică","fi":"Zi","m":"URBAN","la":"VICOVU DE SUS STR  CALEA CERNAUTI NR  342","lt":"0230413016"},{"j":"SV","c":"106","l":"COLEGIUL \"ALEXANDRU CEL BUN\" GURA HUMORULUI","n":"Liceal","sp":"Mecanică","nll":"15","lp":"Limba română","lb":"-","p":"Tehnic","f":"Tehnologică","fi":"Zi","m":"URBAN","la":"GURA HUMORULUI STR BUCOVINA NR 41","lt":"0230235098"},{"j":"SV","c":"219","l":"LICEUL TEHNOLOGIC \"ION NISTOR\" VICOVU DE SUS","n":"Liceal","sp":"Fabricarea produselor din lemn","nll":"14","lp":"Limba română","lb":"-","p":"Tehnic","f":"Tehnologică","fi":"Zi","m":"URBAN","la":"VICOVU DE SUS STR  CALEA CERNAUTI NR  342","lt":"0230413016"},{"j":"SV","c":"203","l":"COLEGIUL \"VASILE LOVINESCU\" FĂLTICENI","n":"Liceal","sp":"Construcţii, instalaţii şi lucrări publice","nll":"19","lp":"Limba română","lb":"-","p":"Tehnic","f":"Tehnologică","fi":"Zi","m":"URBAN","la":"FĂLTICENI STR  MAIOR IOAN NR 10","lt":"0230541215"},{"j":"SV","c":"107","l":"COLEGIUL \"ALEXANDRU CEL BUN\" GURA HUMORULUI","n":"Liceal","sp":"Turism şi alimentaţie","nll":"9","lp":"Limba polonă","lb":"-","p":"Servicii","f":"Tehnologică","fi":"Zi","m":"URBAN","la":"GURA HUMORULUI STR BUCOVINA NR 41","lt":"0230235098"},{"j":"SV","c":"202","l":"COLEGIUL \"VASILE LOVINESCU\" FĂLTICENI","n":"Liceal","sp":"Agricultură","nll":"8","lp":"Limba română","lb":"-","p":"Resurse naturale și protecția mediului","f":"Tehnologică","fi":"Zi","m":"URBAN","la":"FĂLTICENI STR  MAIOR IOAN NR 10","lt":"0230541215"},{"j":"SV","c":"230","l":"LICEUL TEHNOLOGIC \"MIHAI EMINESCU\" DUMBRĂVENI","n":"Liceal","sp":"Mecanică","nll":"4","lp":"Limba română","lb":"-","p":"Tehnic","f":"Tehnologică","fi":"Zi","m":"RURAL","la":"DUMBRĂVENI STR  Principală NR 1732","lt":"0230535014"},{"j":"SV","c":"231","l":"LICEUL TEHNOLOGIC \"NICANOR MOROȘAN\" PÂRTESTII DE JOS","n":"Liceal","sp":"Turism şi alimentaţie","nll":"3","lp":"Limba română","lb":"-","p":"Servicii","f":"Tehnologică","fi":"Zi","m":"RURAL","la":"PÂRTEŞTII DE JOS STR  Solonețului NR 159","lt":"0230237118"},{"j":"SV","c":"218","l":"LICEUL TEHNOLOGIC DORNA CANDRENILOR","n":"Liceal","sp":"Industrie alimentară","nll":"4","lp":"Limba română","lb":"-","p":"Resurse naturale și protecția mediului","f":"Tehnologică","fi":"Zi","m":"RURAL","la":"DORNA CANDRENILOR STR PRINCIPALA NR  88","lt":"0230575171"}]