[{"j":"SJ","c":"103","n":"COLEGIUL NAȚIONAL SILVANIA ZALĂU","noc":33,"nocr":33,"nocnr":0,"t":"Unitate de învăţământ","m":"URBAN","a":"UNIRII 1 450042","p":"0260612598","f":"0260612186"},{"j":"SJ","c":"104","n":"LICEUL CU PROGRAM SPORTIV AVRAM IANCU ZALĂU","noc":43,"nocr":43,"nocnr":0,"t":"Unitate de învăţământ","m":"URBAN","a":"AVRAM IANCU 38 450155","p":"0260613411","f":"0260613411"},{"j":"SJ","c":"105","n":"LICEUL DE ARTĂ IOAN SIMA ZALĂU","noc":37,"nocr":35,"nocnr":2,"t":"Unitate de învăţământ","m":"URBAN","a":"Torentului 9 450118","p":"0260610201","f":"0260610201"},{"j":"SJ","c":"106","n":"LICEUL ORTODOX SF. NICOLAE ZALĂU","noc":9,"nocr":8,"nocnr":1,"t":"Unitate de învăţământ","m":"URBAN","a":"CRIȘAN 15A 450051","p":"0260610842","f":"0260610842"},{"j":"SJ","c":"107","n":"LICEUL REFORMAT WESSELENYI ZALĂU","noc":18,"nocr":18,"nocnr":0,"t":"Unitate de învăţământ","m":"URBAN","a":"MIHAI VITEAZUL 25 450090","p":"0260614881","f":"0372873414"},{"j":"SJ","c":"108","n":"LICEUL TEHNOLOGIC CSEREY-GOGA CRASNA","noc":44,"nocr":44,"nocnr":0,"t":"Unitate de învăţământ","m":"RURAL","a":"PIAȚA EROILOR  14 457085","p":"0260636062","f":"0260636062"},{"j":"SJ","c":"109","n":"LICEUL TEHNOLOGIC IOACHIM POP ILEANDA","noc":14,"nocr":13,"nocnr":1,"t":"Unitate de învăţământ","m":"RURAL","a":"SIMION BARNUTIU 37 457190","p":"0260648728","f":"0260648728"},{"j":"SJ","c":"110","n":"LICEUL TEHNOLOGIC LIVIU REBREANU HIDA","noc":14,"nocr":14,"nocnr":0,"t":"Unitate de învăţământ","m":"RURAL","a":"MIHAI EMINESCU 7 457175","p":"0260628564","f":"0260628564"},{"j":"SJ","c":"111","n":"LICEUL TEHNOLOGIC OCTAVIAN GOGA JIBOU","noc":27,"nocr":24,"nocnr":3,"t":"Unitate de învăţământ","m":"URBAN","a":"WESSELENYI MIKLOS 5 455200","p":"0260644652","f":"0260644652"},{"j":"SJ","c":"112","n":"LICEUL TEHNOLOGIC NR.1 GÂLGĂU","noc":11,"nocr":9,"nocnr":2,"t":"Unitate de învăţământ","m":"RURAL","a":"Principală 28 457140","p":"0260647057","f":"0260647057"},{"j":"SJ","c":"113","n":"LICEUL TEHNOLOGIC NR.1 SURDUC","noc":21,"nocr":20,"nocnr":1,"t":"Unitate de învăţământ","m":"RURAL","a":"Principală  180 457315","p":"0260634808","f":"0260634808"},{"j":"SJ","c":"114","n":"LICEUL TEHNOLOGIC NR.1 SĂRMĂȘAG","noc":17,"nocr":17,"nocnr":0,"t":"Unitate de învăţământ","m":"RURAL","a":"PRIMĂVERII 15 457330","p":"0260655384","f":"0260655026"},{"j":"SJ","c":"115","n":"ȘCOALA GIMNAZIALĂ ADY ENDRE LOMPIRT","noc":4,"nocr":3,"nocnr":1,"t":"Unitate de învăţământ","m":"RURAL","a":"Principală 51 457332","p":null,"f":null},{"j":"SJ","c":"116","n":"ȘCOALA GIMNAZIALĂ ANDREI MUREȘANU CEHU SILVANIEI","noc":40,"nocr":39,"nocnr":1,"t":"Unitate de învăţământ","m":"URBAN","a":"P-TA TRANDAFIRILOR 39 455100","p":"0260650309","f":"0260650309"},{"j":"SJ","c":"117","n":"ȘCOALA GIMNAZIALĂ AURELIA ȘI LAZĂR COSMA TREZNEA","noc":4,"nocr":4,"nocnr":0,"t":"Unitate de învăţământ","m":"RURAL","a":"Pincipală  81 457340","p":"0260658060","f":"0260658060"},{"j":"SJ","c":"118","n":"ȘCOALA GIMNAZIALĂ AVRAM IANCU ALUNIȘ","noc":4,"nocr":4,"nocnr":0,"t":"Unitate de învăţământ","m":"RURAL","a":"PRINCIPALĂ 138 457036","p":"0260654362","f":"0260654362"},{"j":"SJ","c":"119","n":"ȘCOALA GIMNAZIALĂ AVRAM IANCU HALMĂȘD","noc":9,"nocr":9,"nocnr":0,"t":"Unitate de învăţământ","m":"RURAL","a":"Principală 338 457160","p":"0260623006","f":"0260623006"},{"j":"SJ","c":"120","n":"ȘCOALA GIMNAZIALĂ BATHORY ISTVAN ȘIMLEU SILVANIEI","noc":17,"nocr":17,"nocnr":0,"t":"Unitate de învăţământ","m":"URBAN","a":"1 DECEMBRIE 1918 15 455300","p":"0360566956","f":"0360566956"},{"j":"SJ","c":"121","n":"ȘCOALA GIMNAZIALĂ CORNELIU COPOSU ZALĂU","noc":60,"nocr":60,"nocnr":0,"t":"Unitate de învăţământ","m":"URBAN","a":"Bărnuţiu Simion  75 450129","p":"0260612381","f":"0260660784"},{"j":"SJ","c":"122","n":"ȘCOALA GIMNAZIALĂ GEORGE COȘBUC ZALĂU","noc":4,"nocr":4,"nocnr":0,"t":"Unitate de învăţământ","m":"URBAN","a":"MOIGRADULUI 3 450001","p":"0260617687","f":"0260617687"},{"j":"SJ","c":"123","n":"ȘCOALA GIMNAZIALĂ GHEORGHE LAZĂR ZALĂU","noc":63,"nocr":63,"nocnr":0,"t":"Unitate de învăţământ","m":"URBAN","a":"Lazăr Gheorghe 59A 450027","p":"0260615469","f":"0260615469"},{"j":"SJ","c":"124","n":"ȘCOALA GIMNAZIALĂ GHEORGHE MUNTEANU POIANA BLENCHII","noc":5,"nocr":5,"nocnr":0,"t":"Unitate de învăţământ","m":"RURAL","a":"Principală 160 457275","p":"0260635507","f":"0260635647"},{"j":"SJ","c":"125","n":"ȘCOALA GIMNAZIALĂ GHEORGHE ȘINCAI BOBOTA","noc":15,"nocr":14,"nocnr":1,"t":"Unitate de învăţământ","m":"RURAL","a":"Principală 81A 457040","p":"0260652485","f":"0260652485"},{"j":"SJ","c":"126","n":"ȘCOALA GIMNAZIALĂ GYULAFFY LASZLO CEHU SILVANIEI","noc":32,"nocr":32,"nocnr":0,"t":"Unitate de învăţământ","m":"URBAN","a":"UNIRII 4 455100","p":"0260650935","f":"0260650935"},{"j":"SJ","c":"127","n":"ȘCOALA GIMNAZIALĂ HOREA CIZER","noc":13,"nocr":13,"nocnr":0,"t":"Unitate de învăţământ","m":"RURAL","a":"Principală 292 457075","p":"0260625408","f":"0260625515"},{"j":"SJ","c":"128","n":"ȘCOALA GIMNAZIALĂ HOREA ȘIMLEU SILVANIEI","noc":23,"nocr":23,"nocnr":0,"t":"Unitate de învăţământ","m":"URBAN","a":"HOREA 26 455300","p":"0360566006","f":"0360780154"},{"j":"SJ","c":"129","n":"ȘCOALA GIMNAZIALĂ IULIU MANIU ZALĂU","noc":41,"nocr":37,"nocnr":4,"t":"Unitate de învăţământ","m":"URBAN","a":"MIHAI VITEAZUL 35 450010","p":"0260613318","f":"0260613318"},{"j":"SJ","c":"130","n":"ȘCOALA GIMNAZIALĂ LUCIAN BLAGA JIBOU","noc":51,"nocr":48,"nocnr":3,"t":"Unitate de învăţământ","m":"URBAN","a":"GAROAFELOR 7 455200","p":"0260644727","f":"0260644727"},{"j":"SJ","c":"131","n":"ȘCOALA GIMNAZIALĂ MARCUS AURELIUS CREACA","noc":9,"nocr":9,"nocnr":0,"t":"Unitate de învăţământ","m":"RURAL","a":"Principală 173B 457090","p":"0260646517","f":"0260646517"},{"j":"SJ","c":"132","n":"ȘCOALA GIMNAZIALĂ MIHAI EMINESCU ZALĂU","noc":129,"nocr":127,"nocnr":2,"t":"Unitate de învăţământ","m":"URBAN","a":"CRIȘAN 15A 450051","p":"0260612263","f":"0260612263"},{"j":"SJ","c":"133","n":"ȘCOALA GIMNAZIALĂ PETRE DULFU SĂLĂȚIG","noc":5,"nocr":3,"nocnr":2,"t":"Unitate de învăţământ","m":"RURAL","a":"Principală 57 457295","p":"0260650545","f":"0260650545"},{"j":"SJ","c":"134","n":"ȘCOALA GIMNAZIALĂ PETRE HOSSU CHEUD","noc":5,"nocr":5,"nocnr":0,"t":"Unitate de învăţământ","m":"RURAL","a":"Principală 43 457256","p":"0260646251","f":null},{"j":"SJ","c":"135","n":"ȘCOALA GIMNAZIALĂ PETRI MOR NUȘFALĂU","noc":21,"nocr":19,"nocnr":2,"t":"Unitate de învăţământ","m":"RURAL","a":"PETOFI ȘANDOR 16 457260","p":null,"f":null},{"j":"SJ","c":"136","n":"ȘCOALA GIMNAZIALĂ POROLISSUM ZALĂU","noc":37,"nocr":34,"nocnr":3,"t":"Unitate de învăţământ","m":"URBAN","a":"POROLISSUM 9 450076","p":"0260612388","f":"0260612388"},{"j":"SJ","c":"137","n":"ȘCOALA GIMNAZIALĂ SILVANIA ȘIMLEU SILVANIEI","noc":100,"nocr":97,"nocnr":3,"t":"Unitate de învăţământ","m":"URBAN","a":"1 DECEMBRIE 1918 14 455300","p":"0360566964","f":"0360566964"},{"j":"SJ","c":"138","n":"ȘCOALA GIMNAZIALĂ SIMION BĂRNUȚIU BOCȘA","noc":9,"nocr":9,"nocnr":0,"t":"Unitate de învăţământ","m":"RURAL","a":"Principală 74 457045","p":"0260623518","f":"0372873243"},{"j":"SJ","c":"139","n":"ȘCOALA GIMNAZIALĂ SIMION BĂRNUȚIU ZALĂU","noc":66,"nocr":65,"nocnr":1,"t":"Unitate de învăţământ","m":"URBAN","a":"Mihai Viteazul 3 450015","p":"0260616959","f":"0260616959"},{"j":"SJ","c":"140","n":"ȘCOALA GIMNAZIALĂ SZIKSZAI LAJOS ȘAMȘUD","noc":3,"nocr":3,"nocnr":0,"t":"Unitate de învăţământ","m":"RURAL","a":"Principală 124 457325","p":"0260653204","f":"0260653204"},{"j":"SJ","c":"141","n":"ȘCOALA GIMNAZIALĂ TRAIAN CREȚU NĂPRADEA","noc":17,"nocr":17,"nocnr":0,"t":"Unitate de învăţământ","m":"RURAL","a":"Principală 369 457255","p":"0260646212","f":"0260646212"},{"j":"SJ","c":"142","n":"ȘCOALA GIMNAZIALĂ VASILE BREBAN CRIȘENI","noc":3,"nocr":3,"nocnr":0,"t":"Unitate de învăţământ","m":"RURAL","a":"Principală 274 457105","p":"0260616307","f":"0260626307"},{"j":"SJ","c":"143","n":"ȘCOALA GIMNAZIALĂ VASILE LUCĂCEL SOMEȘ ODORHEI","noc":14,"nocr":14,"nocnr":0,"t":"Unitate de învăţământ","m":"RURAL","a":"Principală 235 457310","p":"0260654616","f":"0260654616"},{"j":"SJ","c":"144","n":"ȘCOALA GIMNAZIALĂ ARCHID","noc":2,"nocr":2,"nocnr":0,"t":"Unitate de învăţământ","m":"RURAL","a":"Principală 115 457081","p":"0260653129","f":null},{"j":"SJ","c":"145","n":"ȘCOALA GIMNAZIALĂ COSNICIU DE JOS","noc":13,"nocr":10,"nocnr":3,"t":"Unitate de învăţământ","m":"RURAL","a":"Principală 215 457211","p":null,"f":null},{"j":"SJ","c":"146","n":"ȘCOALA GIMNAZIALĂ DERȘIDA","noc":2,"nocr":1,"nocnr":1,"t":"Unitate de învăţământ","m":"RURAL","a":"Principală 58B 457041","p":null,"f":null},{"j":"SJ","c":"147","n":"ȘCOALA GIMNAZIALĂ GIURTELECU ȘIMLEULUI","noc":5,"nocr":4,"nocnr":1,"t":"Unitate de învăţământ","m":"RURAL","a":"Principală 167 457238","p":"0260671396","f":null},{"j":"SJ","c":"149","n":"ȘCOALA GIMNAZIALĂ GÂLGĂU ALMAȘULUI","noc":11,"nocr":11,"nocnr":0,"t":"Unitate de învăţământ","m":"RURAL","a":"Principală 402 457029","p":"0260628092","f":null},{"j":"SJ","c":"150","n":"ȘCOALA GIMNAZIALĂ IAZ","noc":3,"nocr":1,"nocnr":2,"t":"Unitate de învăţământ","m":"RURAL","a":"Principală 144 457272","p":null,"f":null},{"j":"SJ","c":"152","n":"ȘCOALA GIMNAZIALĂ NR.1 AGHIREȘ","noc":2,"nocr":2,"nocnr":0,"t":"Unitate de învăţământ","m":"RURAL","a":"PRINCIPALĂ 72 457246","p":"0260659093","f":"0260653093"},{"j":"SJ","c":"153","n":"ȘCOALA GIMNAZIALĂ NR.1 AGRIJ","noc":5,"nocr":5,"nocnr":0,"t":"Unitate de învăţământ","m":"RURAL","a":"Principală 46 457005","p":"0260658587","f":"0260658287"},{"j":"SJ","c":"154","n":"ȘCOALA GIMNAZIALĂ NR.1 ALMAȘU","noc":1,"nocr":0,"nocnr":1,"t":"Unitate de învăţământ","m":"RURAL","a":"Principală 251 457010","p":"0260626636","f":"0260626636"},{"j":"SJ","c":"155","n":"ȘCOALA GIMNAZIALĂ NR.1 BOGHIȘ","noc":9,"nocr":8,"nocnr":1,"t":"Unitate de învăţământ","m":"RURAL","a":"Principală 128 457262","p":"0260623709","f":"0260623709"},{"j":"SJ","c":"156","n":"ȘCOALA GIMNAZIALĂ NR.1 BORLA","noc":8,"nocr":8,"nocnr":0,"t":"Unitate de învăţământ","m":"RURAL","a":"Kandia 239 457046","p":"0260623523","f":"0372870216"},{"j":"SJ","c":"157","n":"ȘCOALA GIMNAZIALĂ NR.1 BUCIUMI","noc":17,"nocr":15,"nocnr":2,"t":"Unitate de învăţământ","m":"RURAL","a":"Principală 194 457050","p":"0260624687","f":"0260624687"},{"j":"SJ","c":"158","n":"ȘCOALA GIMNAZIALĂ NR.1 BĂBENI","noc":7,"nocr":5,"nocnr":2,"t":"Unitate de învăţământ","m":"RURAL","a":"PRINCIPALĂ 265 457020","p":"0260634309","f":"0260634309"},{"j":"SJ","c":"159","n":"ȘCOALA GIMNAZIALĂ NR.1 BĂLAN","noc":21,"nocr":21,"nocnr":0,"t":"Unitate de învăţământ","m":"RURAL","a":"PRINCIPALĂ 66  457025","p":"0260664497","f":"0260664497"},{"j":"SJ","c":"160","n":"ȘCOALA GIMNAZIALĂ NR.1 BĂNIȘOR","noc":14,"nocr":14,"nocnr":0,"t":"Unitate de învăţământ","m":"RURAL","a":"Principală 36 457030","p":"0260637504","f":"0260637504"},{"j":"SJ","c":"161","n":"ȘCOALA GIMNAZIALĂ NR.1 CAMĂR","noc":11,"nocr":11,"nocnr":0,"t":"Unitate de învăţământ","m":"RURAL","a":"Principală 273 457060","p":"0260672114","f":"0260672114"},{"j":"SJ","c":"162","n":"ȘCOALA GIMNAZIALĂ NR.1 CARASTELEC","noc":3,"nocr":3,"nocnr":0,"t":"Unitate de învăţământ","m":"RURAL","a":"Principală 463 457065","p":"0260673702","f":"0260673702"},{"j":"SJ","c":"163","n":"ȘCOALA GIMNAZIALĂ NR.1 CHIEȘD","noc":12,"nocr":10,"nocnr":2,"t":"Unitate de învăţământ","m":"RURAL","a":"Principală 368 457070","p":"0260652805","f":"0260652931"},{"j":"SJ","c":"164","n":"ȘCOALA GIMNAZIALĂ NR.1 COȘEIU","noc":1,"nocr":1,"nocnr":0,"t":"Unitate de învăţământ","m":"RURAL","a":"Principală 224 457080","p":"0260653019","f":"0260653019"},{"j":"SJ","c":"165","n":"ȘCOALA GIMNAZIALĂ NR.1 CRISTOLȚ","noc":5,"nocr":5,"nocnr":0,"t":"Unitate de învăţământ","m":"RURAL","a":"Principală 85 457100","p":"0260635959","f":"0260635959"},{"j":"SJ","c":"166","n":"ȘCOALA GIMNAZIALĂ NR.1 CUZĂPLAC","noc":4,"nocr":4,"nocnr":0,"t":"Unitate de învăţământ","m":"RURAL","a":"Principală 242 457110","p":"0260626372","f":"0260626372"},{"j":"SJ","c":"167","n":"ȘCOALA GIMNAZIALĂ NR.1 DEJA","noc":4,"nocr":4,"nocnr":0,"t":"Unitate de învăţământ","m":"RURAL","a":"Principală 138 457297","p":"0260654421","f":"0260654421"},{"j":"SJ","c":"168","n":"ȘCOALA GIMNAZIALĂ NR.1 DOBRIN","noc":2,"nocr":2,"nocnr":0,"t":"Unitate de învăţământ","m":"RURAL","a":"Principală 28 457120","p":"0260668805","f":"0260668805"},{"j":"SJ","c":"169","n":"ȘCOALA GIMNAZIALĂ NR.1 DRAGU","noc":3,"nocr":3,"nocnr":0,"t":"Unitate de învăţământ","m":"RURAL","a":"Principală 330 457130","p":"0260628756","f":"0260628756"},{"j":"SJ","c":"170","n":"ȘCOALA GIMNAZIALĂ NR.1 FILDU DE MIJLOC","noc":5,"nocr":3,"nocnr":2,"t":"Unitate de învăţământ","m":"RURAL","a":"PRINCIPALĂ 31 457136","p":"0260667410","f":"0260667410"},{"j":"SJ","c":"171","n":"ȘCOALA GIMNAZIALĂ NR.1 FĂGETU","noc":1,"nocr":1,"nocnr":0,"t":"Unitate de învăţământ","m":"RURAL","a":"Principală 61 457271","p":null,"f":null},{"j":"SJ","c":"172","n":"ȘCOALA GIMNAZIALĂ NR.1 GÂRBOU","noc":8,"nocr":8,"nocnr":0,"t":"Unitate de învăţământ","m":"RURAL","a":"Principală 50 457150","p":"0260639011","f":"0260639011"},{"j":"SJ","c":"173","n":"ȘCOALA GIMNAZIALĂ NR.1 HERECLEAN","noc":5,"nocr":5,"nocnr":0,"t":"Unitate de învăţământ","m":"RURAL","a":"Principală 32 457165","p":"0260629163","f":"0260629531"},{"j":"SJ","c":"174","n":"ȘCOALA GIMNAZIALĂ NR.1 HOROATU CRASNEI","noc":9,"nocr":9,"nocnr":0,"t":"Unitate de învăţământ","m":"RURAL","a":"Principală 515 457185","p":"0260637448","f":"0260637448"},{"j":"SJ","c":"175","n":"ȘCOALA GIMNAZIALĂ NR.1 IP","noc":20,"nocr":20,"nocnr":0,"t":"Unitate de învăţământ","m":"RURAL","a":"GARII 301 457210","p":"0260671515","f":"0260671545"},{"j":"SJ","c":"176","n":"ȘCOALA GIMNAZIALĂ NR.1 JEBUCU","noc":2,"nocr":2,"nocnr":0,"t":"Unitate de învăţământ","m":"RURAL","a":"Principală 22 457013","p":"0260626104","f":"0260626104"},{"j":"SJ","c":"177","n":"ȘCOALA GIMNAZIALĂ NR.1 LETCA","noc":12,"nocr":10,"nocnr":2,"t":"Unitate de învăţământ","m":"RURAL","a":"Principală 216 457215","p":"0260634535","f":"0260701081"},{"j":"SJ","c":"178","n":"ȘCOALA GIMNAZIALĂ NR.1 LOZNA","noc":2,"nocr":2,"nocnr":0,"t":"Unitate de învăţământ","m":"RURAL","a":"Principală 38 457225","p":"0260635328","f":"0260635328"},{"j":"SJ","c":"179","n":"ȘCOALA GIMNAZIALĂ NR.1 MARCA","noc":14,"nocr":12,"nocnr":2,"t":"Unitate de învăţământ","m":"RURAL","a":"Principală 193 457230","p":"0260679503","f":"0260679593"},{"j":"SJ","c":"180","n":"ȘCOALA GIMNAZIALĂ NR.1 MIRȘID","noc":4,"nocr":4,"nocnr":0,"t":"Unitate de învăţământ","m":"RURAL","a":"Principală 197 457250","p":"0260663501","f":"0260663501"},{"j":"SJ","c":"181","n":"ȘCOALA GIMNAZIALĂ NR.1 MĂERIȘTE","noc":13,"nocr":11,"nocnr":2,"t":"Unitate de învăţământ","m":"RURAL","a":"ȘCOLII 188/A 457235","p":"0260657106","f":"0260657106"},{"j":"SJ","c":"182","n":"ȘCOALA GIMNAZIALĂ NR.1 PANIC","noc":4,"nocr":4,"nocnr":0,"t":"Unitate de învăţământ","m":"RURAL","a":"Principală 100/A 457171","p":"0260629473","f":"0260669854"},{"j":"SJ","c":"183","n":"ȘCOALA GIMNAZIALĂ NR.1 PERICEI","noc":16,"nocr":16,"nocnr":0,"t":"Unitate de învăţământ","m":"RURAL","a":"ȘOSEA 31 457265","p":"0260672705","f":"0260672705"},{"j":"SJ","c":"184","n":"ȘCOALA GIMNAZIALĂ NR.1 PLOPIȘ","noc":10,"nocr":10,"nocnr":0,"t":"Unitate de învăţământ","m":"RURAL","a":"Principală 134 457270","p":"0260671105","f":"0260671105"},{"j":"SJ","c":"185","n":"ȘCOALA GIMNAZIALĂ NR.1 PUSTA","noc":3,"nocr":3,"nocnr":0,"t":"Unitate de învăţământ","m":"URBAN","a":"Mesteacănului 29 455303","p":"0260678191","f":"0360780057"},{"j":"SJ","c":"186","n":"ȘCOALA GIMNAZIALĂ NR.1 ROMÂNAȘI","noc":10,"nocr":10,"nocnr":0,"t":"Unitate de învăţământ","m":"RURAL","a":"Principală 50 457280","p":"0260624115","f":"0260624115"},{"j":"SJ","c":"187","n":"ȘCOALA GIMNAZIALĂ NR.1 RUS","noc":5,"nocr":4,"nocnr":1,"t":"Unitate de învăţământ","m":"RURAL","a":"Bisericii 332 457290","p":"0260639396","f":"0260639396"},{"j":"SJ","c":"188","n":"ȘCOALA GIMNAZIALĂ NR.1 SÂNMIHAIU ALMAȘULUI","noc":11,"nocr":11,"nocnr":0,"t":"Unitate de învăţământ","m":"RURAL","a":"Principală 466 457305","p":"0260627200","f":"0260627200"},{"j":"SJ","c":"189","n":"ȘCOALA GIMNAZIALĂ NR.1 VALCĂU DE JOS","noc":13,"nocr":11,"nocnr":2,"t":"Unitate de învăţământ","m":"RURAL","a":"Principală 100 457345","p":"0260670700","f":"0260670700"},{"j":"SJ","c":"190","n":"ȘCOALA GIMNAZIALĂ NR.1 VÂRȘOLȚ","noc":16,"nocr":16,"nocnr":0,"t":"Unitate de învăţământ","m":"RURAL","a":"Principală 64 457355","p":"0260672506","f":"0360780533"},{"j":"SJ","c":"191","n":"ȘCOALA GIMNAZIALĂ NR.1 ZALHA","noc":3,"nocr":3,"nocnr":0,"t":"Unitate de învăţământ","m":"RURAL","a":"Principală 30 457360","p":"0260639807","f":"0260639807"},{"j":"SJ","c":"192","n":"ȘCOALA GIMNAZIALĂ NR.1 ZIMBOR","noc":3,"nocr":3,"nocnr":0,"t":"Unitate de învăţământ","m":"RURAL","a":"Principală 32 457370","p":"0260627703","f":"0260627703"},{"j":"SJ","c":"194","n":"ȘCOALA GIMNAZIALĂ NR.2 SĂRMĂȘAG","noc":6,"nocr":5,"nocnr":1,"t":"Unitate de învăţământ","m":"RURAL","a":"MINERILOR 15 457330","p":null,"f":null},{"j":"SJ","c":"195","n":"ȘCOALA GIMNAZIALĂ PREOTEASA","noc":5,"nocr":5,"nocnr":0,"t":"Unitate de învăţământ","m":"RURAL","a":"Principală 65 457347","p":null,"f":null},{"j":"SJ","c":"196","n":"ȘCOALA GIMNAZIALĂ STÂRCIU","noc":8,"nocr":8,"nocnr":0,"t":"Unitate de învăţământ","m":"RURAL","a":"Principală 495 457187","p":null,"f":null},{"j":"SJ","c":"197","n":"ȘCOALA GIMNAZIALĂ VALCĂU DE SUS","noc":2,"nocr":2,"nocnr":0,"t":"Unitate de învăţământ","m":"RURAL","a":"Principală 179 457351","p":null,"f":null},{"j":"SJ","c":"198","n":"ȘCOALA PROFESIONALĂ SÂG","noc":15,"nocr":13,"nocnr":2,"t":"Unitate de învăţământ","m":"RURAL","a":"Principală 160 457300","p":"0260673106","f":"0260673106"}]